rwkv_x/__init__.py
rwkv_x/model.py
rwkv_x/rwkv_tokenizer.py
rwkv_x/rwkv_vocab_v20230424.txt
rwkv_x/utils.py
rwkv_x/cuda/gemm_fp16_cublas.cpp
rwkv_x/cuda/operators.cu
rwkv_x/cuda/rwkv7.cu
rwkv_x/cuda/rwkv7_op.cpp
rwkv_x/cuda/wrapper.cpp
rwkv_x-0.1.8.dist-info/licenses/LICENSE
rwkv_x-0.1.8.dist-info/METADATA
rwkv_x-0.1.8.dist-info/WHEEL
rwkv_x-0.1.8.dist-info/top_level.txt
rwkv_x-0.1.8.dist-info/RECORD
