Metadata-Version: 2.4
Name: rwkv-x
Version: 0.1.8
Summary: The RWKV-X Language Model
Author: Haowen HOU
Project-URL: Homepage, https://github.com/howard-hou/RWKV-X
Project-URL: Bug Tracker, https://github.com/howard-hou/RWKV-X/issues
Classifier: Programming Language :: Python :: 3
Classifier: License :: OSI Approved :: Apache Software License
Classifier: Operating System :: OS Independent
Requires-Python: >=3.7
License-File: LICENSE
Dynamic: license-file
